nonebot_plugin_molar_mass/__init__.py
nonebot_plugin_molar_mass/calc.py
nonebot_plugin_molar_mass/elements.json
nonebot_plugin_molar_mass/lexer.py
nonebot_plugin_molar_mass/parser.py
nonebot_plugin_molar_mass-0.2.3.dist-info/LICENSE
nonebot_plugin_molar_mass-0.2.3.dist-info/METADATA
nonebot_plugin_molar_mass-0.2.3.dist-info/WHEEL
nonebot_plugin_molar_mass-0.2.3.dist-info/RECORD
