Metadata-Version: 2.1
Name: nonebot-plugin-molar-mass
Version: 0.2.3
Summary: A tool to calculate molar mass for middle school students.
Home-page: https://github.com/kifuan/nonebot-plugin-molar-mass
Keywords: nonebot,chemistry,molar-mass
Author: kifuan
Author-email: kifuan@foxmail.com
Requires-Python: >=3.9,<4.0
Classifier: Programming Language :: Python :: 3
Classifier: Programming Language :: Python :: 3.9
Classifier: Programming Language :: Python :: 3.10
Classifier: Programming Language :: Python :: 3.11
Requires-Dist: nonebot2[fastapi] (>=2.0.0rc3,<3.0.0)
Requires-Dist: rply (>=0.7.8,<0.8.0)
Project-URL: Repository, https://github.com/kifuan/nonebot-plugin-molar-mass
